<?xml version="1.0" encoding="UTF-8"?>
<persistence>
	<persistence-unit name="materiaPrima">
		<class>materiaPrima.model.PedidoMateriaPrima</class>
		<class>materiaPrima.model.PedidoMateriaPrimaItem</class>
		<jta-data-source>java:/jdbc/materiaPrima-ds</jta-data-source>
		<properties>
			<property name="hibernate.dialect" value="org.hibernate.dialect.SQLServerDialect" />
			<property name="hibernate.hbm2ddl.auto" value="update" />
			<property name="hibernate.show_sql" value="true" />
			<property name="hibernate.format_sql" value="true" />
			<property name="use_sql_comments" value="true" />
		</properties>
	</persistence-unit>
</persistence>
